annoread/__init__.py
annoread/annodata.py
annoread/annoread.py
annoread/assignread.py
annoread/countmtx.py
annoread-0.1.8.dist-info/LICENSE
annoread-0.1.8.dist-info/METADATA
annoread-0.1.8.dist-info/WHEEL
annoread-0.1.8.dist-info/entry_points.txt
annoread-0.1.8.dist-info/top_level.txt
annoread-0.1.8.dist-info/RECORD
