Metadata-Version: 2.1
Name: annoread
Version: 0.1.8
Summary: annotate read from mapping data, and assign the multiple mapped reads, and count
Author-email: Hailing Fang <benjaminfang.ol@outlook.com>
License: MIT License
Project-URL: Homepage, https://github.com/benjaminfang/annoread
Keywords: read annotation,read assignment,read count
Classifier: Programming Language :: Python :: 3
Requires-Python: >=3.11
License-File: LICENSE
Requires-Dist: biobrary>=0.2.1
